treadmdr/__init__.py
treadmdr/def.py
treadmdr-1.0.4.dist-info/LICENSE
treadmdr-1.0.4.dist-info/METADATA
treadmdr-1.0.4.dist-info/WHEEL
treadmdr-1.0.4.dist-info/entry_points.txt
treadmdr-1.0.4.dist-info/top_level.txt
treadmdr-1.0.4.dist-info/RECORD
